airbyte_protocol/models/__init__.py
airbyte_protocol/models/airbyte_protocol.py
airbyte_protocol/models/well_known_types.py
airbyte_protocol_models_pdv2-0.17.1.dist-info/licenses/LICENSE.txt
airbyte_protocol_models_pdv2-0.17.1.dist-info/METADATA
airbyte_protocol_models_pdv2-0.17.1.dist-info/WHEEL
airbyte_protocol_models_pdv2-0.17.1.dist-info/top_level.txt
airbyte_protocol_models_pdv2-0.17.1.dist-info/RECORD
